{
 "allow_comments": 0,
 "allow_delete": 0,
 "allow_edit": 0,
 "allow_incomplete": 0,
 "allow_multiple": 0,
 "allow_print": 0,
 "anonymous": 0,
 "apply_document_permissions": 0,
 "banner_image": "/private/files/most-expensive-cars-in-the-world.webp",
 "button_label": "Book A Ride",
 "condition_json": "[]",
 "creation": "2024-06-07 14:44:54.281622",
 "doc_type": "Ride Order",
 "docstatus": 0,
 "doctype": "Web Form",
 "idx": 0,
 "introduction_text": "<div class=\"ql-editor read-mode\"><p>You can book a ride here </p></div>",
 "is_standard": 1,
 "list_columns": [],
 "login_required": 0,
 "max_attachment_size": 0,
 "modified": "2024-06-07 16:02:21.842906",
 "modified_by": "Administrator",
 "module": "Reltals",
 "name": "order-a-ride",
 "owner": "Administrator",
 "published": 1,
 "route": "order-a-ride",
 "show_attachments": 0,
 "show_list": 0,
 "show_sidebar": 0,
 "title": "order a ride",
 "web_form_fields": [
  {
   "allow_read_on_all_link_options": 0,
   "fieldname": "customer_name",
   "fieldtype": "Data",
   "hidden": 0,
   "label": "Customer Name",
   "max_length": 0,
   "max_value": 0,
   "precision": "",
   "read_only": 0,
   "reqd": 0,
   "show_in_filter": 0
  },
  {
   "allow_read_on_all_link_options": 0,
   "fieldname": "pickup_time",
   "fieldtype": "Datetime",
   "hidden": 0,
   "label": "PickUp Time",
   "max_length": 0,
   "max_value": 0,
   "precision": "",
   "read_only": 0,
   "reqd": 0,
   "show_in_filter": 0
  },
  {
   "allow_read_on_all_link_options": 0,
   "fieldname": "",
   "fieldtype": "Column Break",
   "hidden": 0,
   "label": "",
   "max_length": 0,
   "max_value": 0,
   "options": "",
   "precision": "",
   "read_only": 0,
   "reqd": 0,
   "show_in_filter": 0
  },
  {
   "allow_read_on_all_link_options": 0,
   "fieldname": "contact_number",
   "fieldtype": "Phone",
   "hidden": 0,
   "label": "Contact Number",
   "max_length": 0,
   "max_value": 0,
   "precision": "",
   "read_only": 0,
   "reqd": 0,
   "show_in_filter": 0
  },
  {
   "allow_read_on_all_link_options": 0,
   "fieldname": "vehicle",
   "fieldtype": "Link",
   "hidden": 0,
   "label": "Vehicle",
   "max_length": 0,
   "max_value": 0,
   "options": "Vehicle",
   "precision": "",
   "read_only": 0,
   "reqd": 0,
   "show_in_filter": 0
  },
  {
   "allow_read_on_all_link_options": 0,
   "fieldname": "column_break_mmvt",
   "fieldtype": "Column Break",
   "hidden": 0,
   "label": "",
   "max_length": 0,
   "max_value": 0,
   "precision": "",
   "read_only": 0,
   "reqd": 0,
   "show_in_filter": 0
  },
  {
   "allow_read_on_all_link_options": 0,
   "fieldname": "",
   "fieldtype": "Section Break",
   "hidden": 0,
   "label": "",
   "max_length": 0,
   "max_value": 0,
   "options": "",
   "precision": "",
   "read_only": 0,
   "reqd": 0,
   "show_in_filter": 0
  },
  {
   "allow_read_on_all_link_options": 0,
   "fieldname": "pickup_adress",
   "fieldtype": "Small Text",
   "hidden": 0,
   "label": "Pickup Adress",
   "max_length": 0,
   "max_value": 0,
   "precision": "",
   "read_only": 0,
   "reqd": 0,
   "show_in_filter": 0
  }
 ]
}